{
  "2017-08-07-9546264": {
    "week": "2017-08-07", 
    "date": "2017-08-09", 
    "athlete": 9546264, 
    "distance": 24361.300000000003
  }, 
  "2017-08-07-5088856": {
    "week": "2017-08-07", 
    "date": "2017-08-09", 
    "athlete": 5088856, 
    "distance": 17991.4
  }, 
  "2017-08-07-6880877": {
    "week": "2017-08-07", 
    "date": "2017-08-09", 
    "athlete": 6880877, 
    "distance": 15281.6
  }, 
  "2017-08-07-1407111": {
    "week": "2017-08-07", 
    "date": "2017-08-09", 
    "athlete": 1407111, 
    "distance": 13459.7
  }, 
  "2017-08-07-6684799": {
    "week": "2017-08-07", 
    "date": "2017-08-09", 
    "athlete": 6684799, 
    "distance": 12242.9
  }, 
  "2017-08-07-6900421": {
    "week": "2017-08-07", 
    "date": "2017-08-09", 
    "athlete": 6900421, 
    "distance": 12082.8
  }, 
  "2017-08-07-1320290": {
    "week": "2017-08-07", 
    "date": "2017-08-09", 
    "athlete": 1320290, 
    "distance": 11898.3
  }, 
  "2017-08-07-23936166": {
    "week": "2017-08-07", 
    "date": "2017-08-09", 
    "athlete": 23936166, 
    "distance": 11847.400000000001
  }, 
  "2017-08-07-6885308": {
    "week": "2017-08-07", 
    "date": "2017-08-09", 
    "athlete": 6885308, 
    "distance": 11025.3
  }, 
  "2017-08-07-3342974": {
    "week": "2017-08-07", 
    "date": "2017-08-09", 
    "athlete": 3342974, 
    "distance": 10808.900000000001
  }, 
  "2017-08-07-12986634": {
    "week": "2017-08-07", 
    "date": "2017-08-09", 
    "athlete": 12986634, 
    "distance": 10123.2
  }, 
  "2017-08-07-11961181": {
    "week": "2017-08-07", 
    "date": "2017-08-09", 
    "athlete": 11961181, 
    "distance": 9474.6
  }, 
  "2017-08-07-4907664": {
    "week": "2017-08-07", 
    "date": "2017-08-09", 
    "athlete": 4907664, 
    "distance": 8846.2
  }, 
  "2017-08-07-6112311": {
    "week": "2017-08-07", 
    "date": "2017-08-09", 
    "athlete": 6112311, 
    "distance": 8075.4
  }, 
  "2017-08-07-13750890": {
    "week": "2017-08-07", 
    "date": "2017-08-09", 
    "athlete": 13750890, 
    "distance": 7248.1
  }, 
  "2017-08-07-11509254": {
    "week": "2017-08-07", 
    "date": "2017-08-09", 
    "athlete": 11509254, 
    "distance": 7204.2
  }, 
  "2017-08-07-11293984": {
    "week": "2017-08-07", 
    "date": "2017-08-09", 
    "athlete": 11293984, 
    "distance": 6938.0
  }, 
  "2017-08-07-380546": {
    "week": "2017-08-07", 
    "date": "2017-08-09", 
    "athlete": 380546, 
    "distance": 6454.9
  }, 
  "2017-08-07-14956838": {
    "week": "2017-08-07", 
    "date": "2017-08-09", 
    "athlete": 14956838, 
    "distance": 6235.9
  }, 
  "2017-08-07-6560845": {
    "week": "2017-08-07", 
    "date": "2017-08-09", 
    "athlete": 6560845, 
    "distance": 5636.1
  }, 
  "2017-08-07-1402797": {
    "week": "2017-08-07", 
    "date": "2017-08-09", 
    "athlete": 1402797, 
    "distance": 5372.4
  }, 
  "2017-08-07-6920252": {
    "week": "2017-08-07", 
    "date": "2017-08-09", 
    "athlete": 6920252, 
    "distance": 5267.9
  }, 
  "2017-08-07-3031812": {
    "week": "2017-08-07", 
    "date": "2017-08-09", 
    "athlete": 3031812, 
    "distance": 5180.6
  }, 
  "2017-08-07-6013128": {
    "week": "2017-08-07", 
    "date": "2017-08-09", 
    "athlete": 6013128, 
    "distance": 5029.1
  }, 
  "2017-08-07-1780964": {
    "week": "2017-08-07", 
    "date": "2017-08-09", 
    "athlete": 1780964, 
    "distance": 4023.37
  }, 
  "2017-08-07-11627198": {
    "week": "2017-08-07", 
    "date": "2017-08-09", 
    "athlete": 11627198, 
    "distance": 875.3
  }
}